zeroc/__init__.py
zeroc/compiler.py
zeroc/runtime.py
zeroc-0.2.1.dist-info/METADATA
zeroc-0.2.1.dist-info/WHEEL
zeroc-0.2.1.dist-info/top_level.txt
zeroc-0.2.1.dist-info/RECORD
