Metadata-Version: 2.4
Name: zeroc
Version: 0.2.1
Summary: Run C code directly from Python
Author: Fidal PalamParambil
Author-email: mrfidal@proton.me
Project-URL: Source, https://github.com/mrfidal/zeroc
Classifier: Programming Language :: Python :: 3
Classifier: License :: OSI Approved :: MIT License
Classifier: Operating System :: OS Independent
Requires-Python: >=3.6
Dynamic: author
Dynamic: author-email
Dynamic: classifier
Dynamic: description
Dynamic: description-content-type
Dynamic: project-url
Dynamic: requires-python
Dynamic: summary
